wagglepy/__init__.py
wagglepy/symutil/__init__.py
wagglepy/symutil/basics.py
wagglepy/symutil/characteristics.py
wagglepy/symutil/op.py
wagglepy-0.0.1.dist-info/LICENSE
wagglepy-0.0.1.dist-info/METADATA
wagglepy-0.0.1.dist-info/WHEEL
wagglepy-0.0.1.dist-info/top_level.txt
wagglepy-0.0.1.dist-info/RECORD
