Metadata-Version: 2.1
Name: wagglepy
Version: 0.0.1
Summary: The wagglepy package consists of a collection of template notebooks and some utility functionality for drawing and analyzing the particle traces in the study of plasma physics. Wagglepy, however, does not restrict itself in particle-tracing, but would expand its application across ray-tracing, stochastic procedure and so on, all of which share the same essence, that is, the ordinary differential system.
Home-page: https://github.com/WenyinWei/wagglepy
Author: Wenyin Wei
Author-email: wenyin.wei.ww@gmail.com
License: UNKNOWN
Platform: UNKNOWN
Classifier: Programming Language :: Python :: 3
Classifier: License :: OSI Approved :: MIT License
Classifier: Operating System :: OS Independent
Requires-Python: >=3.6
